video_iframe/__init__.py
video_iframe/video_iframe.py
video_iframe/public/css/video_iframe.css
video_iframe/public/js/src/video_iframe.js
video_iframe/static/README.txt
video_iframe/static/html/video_iframe.html
xblock_video_iframe-1.0.0.dist-info/LICENSE
xblock_video_iframe-1.0.0.dist-info/METADATA
xblock_video_iframe-1.0.0.dist-info/WHEEL
xblock_video_iframe-1.0.0.dist-info/entry_points.txt
xblock_video_iframe-1.0.0.dist-info/top_level.txt
xblock_video_iframe-1.0.0.dist-info/RECORD
