Metadata-Version: 2.1
Name: xblock-video-iframe
Version: 1.0.0
Summary: XBlock to embed video content using iframe along with download buttons
Home-page: https://github.com/open-craft/xblock-video-iframe
Author: OpenCraft
Author-email: help@opencraft.com
License: AGPL 3.0
Keywords: Python edx
Classifier: Development Status :: 3 - Alpha
Classifier: Intended Audience :: Developers
Classifier: License :: OSI Approved :: GNU Affero General Public License v3 or later (AGPLv3+)
Classifier: Natural Language :: English
Classifier: Programming Language :: Python :: 3
Classifier: Programming Language :: Python :: 3.8
Requires-Python: >=3.8
License-File: LICENSE
Requires-Dist: Mako
Requires-Dist: XBlock
Requires-Dist: django-statici18n
Requires-Dist: edx-i18n-tools
Requires-Dist: xblock-utils
